setup_client.py
client/__init__.py
client/client.py
client/build/__init__.py
client/build/lib/__init__.py
client/build/lib/client/__init__.py
client/build/lib/client/add_contact.py
client/build/lib/client/database.py
client/build/lib/client/del_contact.py
client/build/lib/client/main_window.py
client/build/lib/client/main_window_conv.py
client/build/lib/client/start_dialog.py
client/build/lib/client/transport.py
client/build/lib/common/__init__.py
client/build/lib/common/decos.py
client/build/lib/common/descryptors.py
client/build/lib/common/errors.py
client/build/lib/common/metaclasses.py
client/build/lib/common/utils.py
client/build/lib/common/variables.py
client/build/lib/logs/__init__.py
client/build/lib/logs/config_client_log.py
client/build/lib/logs/config_server_log.py
client/build/lib/unit_tests/__init__.py
client/client/__init__.py
client/client/add_contact.py
client/client/database.py
client/client/del_contact.py
client/client/main_window.py
client/client/main_window_conv.py
client/client/start_dialog.py
client/client/transport.py
client/common/__init__.py
client/common/decos.py
client/common/descryptors.py
client/common/errors.py
client/common/metaclasses.py
client/common/utils.py
client/common/variables.py
client/doc/__init__.py
client/doc/source/__init__.py
client/doc/source/conf.py
client/logs/__init__.py
client/logs/config_client_log.py
client/logs/config_server_log.py
client/unit_tests/__init__.py
mes_client_prod.egg-info/PKG-INFO
mes_client_prod.egg-info/SOURCES.txt
mes_client_prod.egg-info/dependency_links.txt
mes_client_prod.egg-info/requires.txt
mes_client_prod.egg-info/top_level.txt