Metadata-Version: 2.1
Name: mes-client-prod
Version: 0.0.2
Summary: mes_client_prod
Home-page: UNKNOWN
Author: Ruslan Zakirov
Author-email: zakirovra@gmail.com
License: UNKNOWN
Platform: UNKNOWN
